mas/__init__.py
mas/convolution.py
mas/csbs.py
mas/data.py
mas/deconvolution.py
mas/decorators.py
mas/forward_model.py
mas/photon_sieve.py
mas/plotting.py
mas/psf_generator.py
mas/random_cost.py
mas/sse_cost.py
mas/strand_generator.py
mas/tracking.py
uiuc_mas-2.dist-info/METADATA
uiuc_mas-2.dist-info/WHEEL
uiuc_mas-2.dist-info/top_level.txt
uiuc_mas-2.dist-info/RECORD
