Metadata-Version: 2.1
Name: uiuc-mas
Version: 2
Summary: Milliarc-second Photon Sieve Simulations
Home-page: https://github.com/uiuc-sine/mas
Author: Evan Widloski
Author-email: evan@evanw.org
License: GPLv3
Keywords: photonsieve csbs sieve uiuc
Platform: UNKNOWN
Classifier: Programming Language :: Python :: 3
Requires-Dist: matplotlib
Requires-Dist: h5py
Requires-Dist: numpy
Requires-Dist: scipy
Requires-Dist: imageio
